discord/ext/ipcs/__init__.py
discord/ext/ipcs/client.py
discord/ext/ipcs/errors.py
discord/ext/ipcs/items.py
discord/ext/ipcs/server.py
discord_ext_ipcs-0.0.4.dist-info/LICENSE
discord_ext_ipcs-0.0.4.dist-info/METADATA
discord_ext_ipcs-0.0.4.dist-info/WHEEL
discord_ext_ipcs-0.0.4.dist-info/top_level.txt
discord_ext_ipcs-0.0.4.dist-info/RECORD
