Metadata-Version: 2.1
Name: discord-ext-ipcs
Version: 0.0.4
Summary: Discord ipc client.
Home-page: https://github.com/tuna2134/discord-ext-ipcs
Author: DMS
Author-email: masato190411@gmail.com
License: UNKNOWN
Platform: UNKNOWN
Classifier: Programming Language :: Python :: 3.9
Classifier: License :: OSI Approved :: MIT License
Classifier: Operating System :: OS Independent
License-File: LICENSE
Requires-Dist: websockets
Requires-Dist: discord.py
Provides-Extra: speed
Requires-Dist: orjson ; extra == 'speed'
